finaletoolkit/__init__.py
finaletoolkit/version.py
finaletoolkit/__pycache__/__init__.cpython-313.pyc
finaletoolkit/__pycache__/version.cpython-313.pyc
finaletoolkit/cli/__init__.py
finaletoolkit/cli/main_cli.py
finaletoolkit/frag/__init__.py
finaletoolkit/frag/_adjust_wps.py
finaletoolkit/frag/_breakpoint_motifs.py
finaletoolkit/frag/_cleavage_profile.py
finaletoolkit/frag/_coverage.py
finaletoolkit/frag/_delfi.py
finaletoolkit/frag/_delfi_gc_correct.py
finaletoolkit/frag/_delfi_merge_bins.py
finaletoolkit/frag/_end_motifs.py
finaletoolkit/frag/_frag_length.py
finaletoolkit/frag/_multi_wps.py
finaletoolkit/frag/_wps.py
finaletoolkit/frag/data/end_motif_f_profiles.tsv
finaletoolkit/genome/__init__.py
finaletoolkit/genome/gaps.py
finaletoolkit/genome/data/hg19.gap.txt.gz
finaletoolkit/genome/data/hg38.gap.txt.gz
finaletoolkit/utils/__init__.py
finaletoolkit/utils/_agg_bw.py
finaletoolkit/utils/_deprecation.py
finaletoolkit/utils/_filter_file.py
finaletoolkit/utils/typing.py
finaletoolkit/utils/utils.py
finaletoolkit-0.11.0.dist-info/licenses/LICENSE
finaletoolkit-0.11.0.dist-info/METADATA
finaletoolkit-0.11.0.dist-info/WHEEL
finaletoolkit-0.11.0.dist-info/entry_points.txt
finaletoolkit-0.11.0.dist-info/top_level.txt
finaletoolkit-0.11.0.dist-info/RECORD
