Metadata-Version: 2.4
Name: FinaleToolkit
Version: 0.11.0
Summary: FinaleToolkit is a package and standalone program to extract fragmentation features of cell-free DNA from paired-end sequencing data.
Author-email: James Li <lijw21@wfu.edu>, Ravi Bandaru <ravi.bandaru@northwestern.edu>, Yaping Liu <yaping@northwestern.edu>
License: MIT License
Project-URL: Homepage, https://epifluidlab.github.io/FinaleToolkit/
Project-URL: Repository, https://github.com/epifluidlab/finaletoolkit
Project-URL: Issues, https://github.com/epifluidlab/FinaleToolkit/issues
Project-URL: Changelog, https://github.com/epifluidlab/FinaleToolkit/blob/main/CHANGELOG.md
Project-URL: Wiki, https://github.com/epifluidlab/FinaleToolkit/wiki
Project-URL: Lab Website, https://epifluidlab.github.io/
Keywords: bioinformatics,cell free DNA,computational biology,genomics,epigenomics
Classifier: Programming Language :: Python :: 3
Classifier: License :: OSI Approved :: MIT License
Classifier: Operating System :: MacOS
Classifier: Operating System :: POSIX :: Linux
Classifier: Topic :: Scientific/Engineering :: Bio-Informatics
Requires-Python: >=3.9
License-File: LICENSE
Requires-Dist: numpy>=2
Requires-Dist: pysam
Requires-Dist: pybigwig
Requires-Dist: py2bit
Requires-Dist: tqdm
Requires-Dist: numba
Requires-Dist: scipy
Requires-Dist: pandas
Requires-Dist: statsmodels
Requires-Dist: loess
Requires-Dist: matplotlib
Dynamic: license-file
